lightshifts/__init__.py
lightshifts/atom.py
lightshifts/auxiliary.py
lightshifts/consts.py
lightshifts/lightshift_solver.py
lightshifts-1.0.dist-info/licenses/LICENSE
lightshifts-1.0.dist-info/METADATA
lightshifts-1.0.dist-info/WHEEL
lightshifts-1.0.dist-info/top_level.txt
lightshifts-1.0.dist-info/RECORD
