Metadata-Version: 2.4
Name: lightshifts
Version: 1.0
Summary: Calculate dynamical scalar, vector and tensor light shifts.
Author: Luis Riegger
Author-email: lri@me.com
Project-URL: homepage, https://github.com/himbeles/lightshifts
Project-URL: repository, https://github.com/himbeles/lightshifts
Keywords: physics,cold atoms,lightshift,hyperfine,coupling
Requires-Python: >=3.11
License-File: LICENSE
Requires-Dist: numpy>2.0
Requires-Dist: sympy>1.1
Requires-Dist: pandas>0.22
Requires-Dist: matplotlib
Dynamic: license-file
